Locker_Project/CMD_Process.py
Locker_Project/CMD_ScanInput.py
Locker_Project/CMD_Thread.py
Locker_Project/Func.py
Locker_Project/Locker.py
Locker_Project/__init__.py
Locker_Pro-0.0.2.dist-info/LICENSE
Locker_Pro-0.0.2.dist-info/METADATA
Locker_Pro-0.0.2.dist-info/WHEEL
Locker_Pro-0.0.2.dist-info/top_level.txt
Locker_Pro-0.0.2.dist-info/RECORD
